codaledgercli
