Metadata-Version: 2.1
Name: coda-ledger-cli
Version: 0.0.5
Summary: Scripts to interact with the Coda Ledger app
Home-page: https://github.com/rbkhmrcr/ledger-big-curves/
Author: Rebekah Mercer
Author-email: rebekah@o1labs.org
License: UNKNOWN
Platform: UNKNOWN
Classifier: Programming Language :: Python :: 3
Classifier: License :: OSI Approved :: MIT License
Classifier: Operating System :: OS Independent
Requires-Python: >=3.6
